kf5py.py
setup.cfg
setup.py
kf5py.egg-info/PKG-INFO
kf5py.egg-info/SOURCES.txt
kf5py.egg-info/dependency_links.txt
kf5py.egg-info/requires.txt
kf5py.egg-info/top_level.txt