Metadata-Version: 1.1
Name: kf5py
Version: 0.1.0
Summary: Python-based utilities for KF5.
Home-page: http://problemshift.github.io/kf5py/
Author: Chris Teplovs
Author-email: dr.chris@problemshift.com
License: LICENSE.txt
Platform: UNKNOWN
Classifier: Programming Language :: Python
Classifier: Programming Language :: Python :: 2
Classifier: Programming Language :: Python :: 3
Classifier: Development Status :: 3 - Alpha
Classifier: Intended Audience :: Science/Research
Classifier: License :: OSI Approved :: MIT License
Classifier: Operating System :: OS Independent
